{
	"configurations" : 
	[
		{
			"directories" : 
			[
				{
					"build" : ".",
					"jsonFile" : "directory-.-Debug-f5ebdc15457944623624.json",
					"minimumCMakeVersion" : 
					{
						"string" : "3.10"
					},
					"projectIndex" : 0,
					"source" : ".",
					"targetIndexes" : 
					[
						0,
						1
					]
				}
			],
			"name" : "Debug",
			"projects" : 
			[
				{
					"directoryIndexes" : 
					[
						0
					],
					"name" : "lib_app",
					"targetIndexes" : 
					[
						0,
						1
					]
				}
			],
			"targets" : 
			[
				{
					"directoryIndex" : 0,
					"id" : "app::@6890427a1f51a3e7e1df",
					"jsonFile" : "target-app-Debug-f33259d09a838324cb7e.json",
					"name" : "app",
					"projectIndex" : 0
				},
				{
					"directoryIndex" : 0,
					"id" : "libapp::@6890427a1f51a3e7e1df",
					"jsonFile" : "target-libapp-Debug-62701c925dafc28964df.json",
					"name" : "libapp",
					"projectIndex" : 0
				}
			]
		}
	],
	"kind" : "codemodel",
	"paths" : 
	{
		"build" : "/home/admin1/code/lib/build",
		"source" : "/home/admin1/code/lib"
	},
	"version" : 
	{
		"major" : 2,
		"minor" : 6
	}
}
